{
  "step": 3,
  "description": "Create expanded task database - Part 2 (Categories 4-7: Social, Creative, Admin, Self-Care)",
  "timestamp": "2026-03-07T08:52:00Z",
  "status": "completed",
  "results": {
    "fileCreated": "projects/tiny-wins-v5-tasks-part2.js",
    "categoriesCompleted": 4,
    "tasksPerCategory": 50,
    "totalTasksCreated": 200,
    "categories": [
      {
        "id": "social",
        "title": "Social Connection",
        "taskTypes": [
          "Communication",
          "Relationship building",
          "Boundaries",
          "Community",
          "Kindness"
        ]
      },
      {
        "id": "creative",
        "title": "Creative Expression",
        "taskTypes": [
          "Writing",
          "Visual art",
          "Music",
          "Crafts",
          "Design"
        ]
      },
      {
        "id": "admin",
        "title": "Admin & Life Stuff",
        "taskTypes": [
          "Digital organization",
          "Financial tasks",
          "Appointments",
          "Planning",
          "Maintenance"
        ]
      },
      {
        "id": "selfcare",
        "title": "Self-Care & Comfort",
        "taskTypes": [
          "Physical care",
          "Relaxation",
          "Comfort",
          "Nature",
          "Self-compassion"
        ]
      }
    ],
    "databaseComplete": true,
    "totalTasksInDatabase": 350,
    "nextSteps": [
      "Merge task files into main app",
      "Implement random task selection",
      "Fix/remove text entry box",
      "Enhance celebration system"
    ]
  }
}
