{
  "step": 2,
  "description": "Create fixed Tiny Wins V5 using V4 base",
  "timestamp": "2026-03-07T15:57:00Z",
  "status": "completed",
  "taskId": "tinywins-v5-fix",
  "taskDescription": "FIX CRITICAL: Rebuild Tiny Wins V5 using V4 as base - categories not loading",
  "notes": "Successfully created fixed V5 version. Key fixes: 1) Uses V4's proven render structure, 2) All 350 tasks in database (50 per category), 3) Categories render immediately on page load, 4) Growth system and enhanced celebrations working, 5) Shuffle button randomly selects 10 tasks from each category's 50 tasks.",
  "deliverable": "projects/tiny-wins-v5.html",
  "fileSize": "31547 bytes",
  "lines": 578,
  "features": [
    "7 categories with 50 tasks each (350 total)",
    "Categories render immediately on load",
    "Shuffle selects 10 random tasks per category",
    "Growth garden with 7 stages (Seedling to Legendary Grove)",
    "Enhanced celebrations with confetti",
    "Streak tracking and persistence",
    "Done list with timestamps"
  ]
}
